Workbook
Name aporte: 'FA INVEST'!$E$12:$E$12
Name invest: 'FA INVEST'!$E$12:$E$12
Name patrimonio: 'FA INVEST'!$E$15:$E$15
Name rendimento_carteira: 'FA INVEST'!$E$8:$E$8
Name rendimento_invest: 'FA INVEST'!$E$14:$E$14
Name salario: 'FA INVEST'!$E$7:$E$7
Name sugestao_invest: 'FA INVEST'!$E$9:$E$9
Name tempo_anos: 'FA INVEST'!$E$13:$E$13

Sheet FA INVEST
A1: FA INVEST
C6: Configurações
C7: Salário | E7: 1000
C8: Redimento carteira | E8: 0.01
C9: Sugestão de investimento | E9: {=salario*30%} -> 300
C11: Investimento mensal
C12: Quanto investir por mês? | E12: 200
B13: 2 | C13: Por quantos anos? | E13: 3
B14: 5 | C14: Taxa de Rendimento mensal? | E14: 0.01
B15: 10 | C15: Patrimonio acumulado? | E15: {=FV(rendimento_invest,tempo_anos*12,aporte*-1)} -> 8615.3757
B16: 20 | C16: Dividendos mensais? | E16: =E15*1% -> 86.153757
B17: 30
C19: Cenários | E19: Dividendos
C20: Investimento caso 2 anos | D20: =FV($E$14,$B13*12,$E$12*-1) -> 5394.693 | E20: {=D20*rendimento_carteira} -> 53.94693
C21: Investimento caso 5 anos | D21: =FV($E$14,$B14*12,$E$12*-1) -> 16333.934 | E21: {=D21*rendimento_carteira} -> 163.33934
C22: Investimento caso 10 anos | D22: =FV($E$14,$B15*12,$E$12*-1) -> 46007.738 | E22: {=D22*rendimento_carteira} -> 460.07738
C23: Investimento caso 20 anos | D23: =FV($E$14,$B16*12,$E$12*-1) -> 197851.07 | E23: {=D23*rendimento_carteira} -> 1978.5107
C24: Investimento caso 30 anos | D24: =FV($E$14,$B17*12,$E$12*-1) -> 698992.83 | E24: {=D24*rendimento_carteira} -> 6989.9283
C30: PERFIL | E30: Moderado
C31: VALOR A SER INVESTIDO POR MÊS | E31: {=aporte} -> 200
C33: TIPO DE FII | D33: Percentual Sugerido | E33: Valores
C34: PAPEL | D34: =VLOOKUP($E$30&"-"&C34,'Tabela de Apoio'!B4:E21,4,FALSE) -> 0.32 | E34: {=aporte*D34} -> 64
C35: TIJOLO | D35: =VLOOKUP($E$30&"-"&C35,'Tabela de Apoio'!B5:E22,4,FALSE) -> 0.35 | E35: {=aporte*D35} -> 70
C36: HÍBRIDOS | D36: =VLOOKUP($E$30&"-"&C36,'Tabela de Apoio'!B6:E23,4,FALSE) -> 0.08 | E36: {=aporte*D36} -> 16
C37: FOFs | D37: =VLOOKUP($E$30&"-"&C37,'Tabela de Apoio'!B7:E24,4,FALSE) -> 0.05 | E37: {=aporte*D37} -> 10
C38: DESENVOLVIMENTO | D38: =VLOOKUP($E$30&"-"&C38,'Tabela de Apoio'!B8:E25,4,FALSE) -> 0.1 | E38: {=aporte*D38} -> 20
C39: HOTELARIAS | D39: =VLOOKUP($E$30&"-"&C39,'Tabela de Apoio'!B9:E26,4,FALSE) -> 0.1 | E39: {=aporte*D39} -> 20

Sheet Tabela de Apoio
B3: CHAVE | C3: PERFIL | D3: TIPO DE FII | E3: % | H3: Cressimento de investimento ao longo de 30 anos do valor investido
B4: Conservador-PAPEL | C4: Conservador | D4: PAPEL | E4: 0.3 | H4: Quatidade messes | I4: Valor estimado | J4: Valor estimado
B5: Conservador-TIJOLO | C5: Conservador | D5: TIJOLO | E5: 0.5 | H5: 1 | I5: {=FV(rendimento_invest,H5*12,aporte*-1)} -> 2536.5006 | J5: {=FV(rendimento_invest,H5*12,sugestao_invest*-1)} -> 3804.7509
B6: Conservador-HÍBRIDOS | C6: Conservador | D6: HÍBRIDOS | E6: 0.1 | H6: 2 | I6: {=FV(rendimento_invest,H6*12,aporte*-1)} -> 5394.693 | J6: {=FV(rendimento_invest,H6*12,sugestao_invest*-1)} -> 8092.0395
B7: Conservador-FOFs | C7: Conservador | D7: FOFs | E7: 0.1 | H7: 3 | I7: {=FV(rendimento_invest,H7*12,aporte*-1)} -> 8615.3757 | J7: {=FV(rendimento_invest,H7*12,sugestao_invest*-1)} -> 12923.064
B8: Conservador-DESENVOLVIMENTO | C8: Conservador | D8: DESENVOLVIMENTO | E8: 0 | H8: 4 | I8: {=FV(rendimento_invest,H8*12,aporte*-1)} -> 12244.522 | J8: {=FV(rendimento_invest,H8*12,sugestao_invest*-1)} -> 18366.782
B9: Conservador-HOTELARIAS | C9: Conservador | D9: HOTELARIAS | E9: 0 | H9: 5 | I9: {=FV(rendimento_invest,H9*12,aporte*-1)} -> 16333.934 | J9: {=FV(rendimento_invest,H9*12,sugestao_invest*-1)} -> 24500.901
B10: Moderado-PAPEL | C10: Moderado | D10: PAPEL | E10: 0.32 | H10: 6 | I10: {=FV(rendimento_invest,H10*12,aporte*-1)} -> 20941.986 | J10: {=FV(rendimento_invest,H10*12,sugestao_invest*-1)} -> 31412.979
B11: Moderado-TIJOLO | C11: Moderado | D11: TIJOLO | E11: 0.35 | H11: 7 | I11: {=FV(rendimento_invest,H11*12,aporte*-1)} -> 26134.455 | J11: {=FV(rendimento_invest,H11*12,sugestao_invest*-1)} -> 39201.682
B12: Moderado-HÍBRIDOS | C12: Moderado | D12: HÍBRIDOS | E12: 0.08 | H12: 8 | I12: {=FV(rendimento_invest,H12*12,aporte*-1)} -> 31985.459 | J12: {=FV(rendimento_invest,H12*12,sugestao_invest*-1)} -> 47978.188
B13: Moderado-FOFs | C13: Moderado | D13: FOFs | E13: 0.05 | H13: 9 | I13: {=FV(rendimento_invest,H13*12,aporte*-1)} -> 38578.516 | J13: {=FV(rendimento_invest,H13*12,sugestao_invest*-1)} -> 57867.774
B14: Moderado-DESENVOLVIMENTO | C14: Moderado | D14: DESENVOLVIMENTO | E14: 0.1 | H14: 10 | I14: {=FV(rendimento_invest,H14*12,aporte*-1)} -> 46007.738 | J14: {=FV(rendimento_invest,H14*12,sugestao_invest*-1)} -> 69011.607
B15: Moderado-HOTELARIAS | C15: Moderado | D15: HOTELARIAS | E15: 0.1 | H15: 11 | I15: {=FV(rendimento_invest,H15*12,aporte*-1)} -> 54379.171 | J15: {=FV(rendimento_invest,H15*12,sugestao_invest*-1)} -> 81568.757
B16: Agressivo-PAPEL | C16: Agressivo | D16: PAPEL | E16: 0.5 | H16: 12 | I16: {=FV(rendimento_invest,H16*12,aporte*-1)} -> 63812.312 | J16: {=FV(rendimento_invest,H16*12,sugestao_invest*-1)} -> 95718.468
... B21: Agressivo-HOTELARIAS | C21: Agressivo | D21: HOTELARIAS | E21: 0.1 | H21: 17 | I21: {=FV(rendimento_invest,H21*12,aporte*-1)} -> 132261.55 | J21: {=FV(rendimento_invest,H21*12,sugestao_invest*-1)} -> 198392.33
H22: 18 | I22: {=FV(rendimento_invest,H22*12,aporte*-1)} -> 151572.13 | J22: {=FV(rendimento_invest,H22*12,sugestao_invest*-1)} -> 227358.19
H23: 19 | I23: {=FV(rendimento_invest,H23*12,aporte*-1)} -> 173331.77 | J23: {=FV(rendimento_invest,H23*12,sugestao_invest*-1)} -> 259997.65
H24: 20 | I24: {=FV(rendimento_invest,H24*12,aporte*-1)} -> 197851.07 | J24: {=FV(rendimento_invest,H24*12,sugestao_invest*-1)} -> 296776.61
H25: 21 | I25: {=FV(rendimento_invest,H25*12,aporte*-1)} -> 225480.04 | J25: {=FV(rendimento_invest,H25*12,sugestao_invest*-1)} -> 338220.06
H26: 22 | I26: {=FV(rendimento_invest,H26*12,aporte*-1)} -> 256613.06 | J26: {=FV(rendimento_invest,H26*12,sugestao_invest*-1)} -> 384919.58
H27: 23 | I27: {=FV(rendimento_invest,H27*12,aporte*-1)} -> 291694.51 | J27: {=FV(rendimento_invest,H27*12,sugestao_invest*-1)} -> 437541.77
H28: 24 | I28: {=FV(rendimento_invest,H28*12,aporte*-1)} -> 331225.18 | J28: {=FV(rendimento_invest,H28*12,sugestao_invest*-1)} -> 496837.77
H29: 25 | I29: {=FV(rendimento_invest,H29*12,aporte*-1)} -> 375769.33 | J29: {=FV(rendimento_invest,H29*12,sugestao_invest*-1)} -> 563653.99
H30: 26 | I30: {=FV(rendimento_invest,H30*12,aporte*-1)} -> 425962.78 | J30: {=FV(rendimento_invest,H30*12,sugestao_invest*-1)} -> 638944.17
H31: 27 | I31: {=FV(rendimento_invest,H31*12,aporte*-1)} -> 482522.03 | J31: {=FV(rendimento_invest,H31*12,sugestao_invest*-1)} -> 723783.04
H32: 28 | I32: {=FV(rendimento_invest,H32*12,aporte*-1)} -> 546254.4 | J32: {=FV(rendimento_invest,H32*12,sugestao_invest*-1)} -> 819381.59
H33: 29 | I33: {=FV(rendimento_invest,H33*12,aporte*-1)} -> 618069.63 | J33: {=FV(rendimento_invest,H33*12,sugestao_invest*-1)} -> 927104.44
H34: 30 | I34: {=FV(rendimento_invest,H34*12,aporte*-1)} -> 698992.83 | J34: {=FV(rendimento_invest,H34*12,sugestao_invest*-1)} -> 1048489.2
